README.md
setup.py
notify_server/__init__.py
notify_server/__main__.py
notify_server/event_system.py
notify_server/socket_server.py
notify_server.egg-info/PKG-INFO
notify_server.egg-info/SOURCES.txt
notify_server.egg-info/dependency_links.txt
notify_server.egg-info/entry_points.txt
notify_server.egg-info/requires.txt
notify_server.egg-info/top_level.txt